pictools/__init__.py
pictools/__main__.py
pictools/programmer-version.txt
pictools/programmer.bin
pictools-0.17.0.dist-info/DESCRIPTION.rst
pictools-0.17.0.dist-info/METADATA
pictools-0.17.0.dist-info/RECORD
pictools-0.17.0.dist-info/WHEEL
pictools-0.17.0.dist-info/entry_points.txt
pictools-0.17.0.dist-info/metadata.json
pictools-0.17.0.dist-info/top_level.txt
tests/__init__.py
tests/serial.py
tests/target.py
tests/test_pictools.py
