Metadata-Version: 2.0
Name: pictools
Version: 0.17.0
Summary: PIC tools.
Home-page: https://github.com/eerimoq/pictools
Author: Erik Moqvist
Author-email: erik.moqvist@gmail.com
License: MIT
Keywords: pic,pic32,programmer
Platform: UNKNOWN
Classifier: License :: OSI Approved :: MIT License
Classifier: Programming Language :: Python :: 3
Requires-Dist: bincopy
Requires-Dist: bitstruct
Requires-Dist: pyserial
Requires-Dist: tqdm
